twitpy/__init__.py
twitpy-1.0.3.dist-info/License.txt
twitpy-1.0.3.dist-info/METADATA
twitpy-1.0.3.dist-info/WHEEL
twitpy-1.0.3.dist-info/top_level.txt
twitpy-1.0.3.dist-info/RECORD
