Metadata-Version: 2.1
Name: twitpy
Version: 1.0.3
Summary: A package based on the twitter api, search users of twitter and MORE!.
Home-page: UNKNOWN
License: UNKNOWN
Platform: UNKNOWN
Classifier: Programming Language :: Python :: 3
Classifier: License :: OSI Approved :: MIT License
Classifier: Operating System :: OS Independent
Requires-Python: >=3.6
Requires-Dist: tweepy
